edpanalyst/__init__.py
edpanalyst/api.py
edpanalyst/config.py
edpanalyst/guess.py
edpanalyst/guess_test.py
edpanalyst/plot.py
edpanalyst/population.py
edpanalyst/population_model.py
edpanalyst/population_schema.py
edpanalyst/population_schema_test.py
edpanalyst/rowids.py
edpanalyst/session.py
edpanalyst/session_experimental.py
edpanalyst/session_test.py
edpanalyst-0.1.16.dist-info/DESCRIPTION.rst
edpanalyst-0.1.16.dist-info/METADATA
edpanalyst-0.1.16.dist-info/RECORD
edpanalyst-0.1.16.dist-info/WHEEL
edpanalyst-0.1.16.dist-info/metadata.json
edpanalyst-0.1.16.dist-info/top_level.txt
