Metadata-Version: 2.0
Name: edpanalyst
Version: 0.1.16
Summary: The python API to the Empirical Data Platform.
Home-page: UNKNOWN
Author: UNKNOWN
Author-email: UNKNOWN
License: Apache License 2.0
Platform: UNKNOWN
Requires-Dist: beautifulsoup4
Requires-Dist: configparser
Requires-Dist: future
Requires-Dist: natsort
Requires-Dist: pandas
Requires-Dist: requests
Requires-Dist: typing
Requires-Dist: enum34
Requires-Dist: python-dateutil
